InterviewtopHulianwangMianshiBaguwen/README.md
InterviewtopHulianwangMianshiBaguwen/__init__.py
InterviewtopHulianwangMianshiBaguwen/__main__.py
InterviewtopHulianwangMianshiBaguwen/file.epub
InterviewtopHulianwangMianshiBaguwen/index.html
InterviewtopHulianwangMianshiBaguwen/css/__init__.py
InterviewtopHulianwangMianshiBaguwen/css/annotations.css
InterviewtopHulianwangMianshiBaguwen/css/main.css
InterviewtopHulianwangMianshiBaguwen/css/normalize.css
InterviewtopHulianwangMianshiBaguwen/css/popup.css
InterviewtopHulianwangMianshiBaguwen/font/__init__.py
InterviewtopHulianwangMianshiBaguwen/font/fontello.eot
InterviewtopHulianwangMianshiBaguwen/font/fontello.svg
InterviewtopHulianwangMianshiBaguwen/font/fontello.ttf
InterviewtopHulianwangMianshiBaguwen/font/fontello.woff
InterviewtopHulianwangMianshiBaguwen/img/__init__.py
InterviewtopHulianwangMianshiBaguwen/img/annotator-glyph-sprite.png
InterviewtopHulianwangMianshiBaguwen/img/annotator-icon-sprite.png
InterviewtopHulianwangMianshiBaguwen/img/apple-touch-icon.png
InterviewtopHulianwangMianshiBaguwen/img/cancelfullscreen.png
InterviewtopHulianwangMianshiBaguwen/img/close.png
InterviewtopHulianwangMianshiBaguwen/img/fullscreen.png
InterviewtopHulianwangMianshiBaguwen/img/loader.gif
InterviewtopHulianwangMianshiBaguwen/img/menu-icon.png
InterviewtopHulianwangMianshiBaguwen/img/save.png
InterviewtopHulianwangMianshiBaguwen/img/saved.png
InterviewtopHulianwangMianshiBaguwen/img/settings-s.png
InterviewtopHulianwangMianshiBaguwen/img/settings.png
InterviewtopHulianwangMianshiBaguwen/img/star.png
InterviewtopHulianwangMianshiBaguwen/js/__init__.py
InterviewtopHulianwangMianshiBaguwen/js/epub.js
InterviewtopHulianwangMianshiBaguwen/js/epub.min.js
InterviewtopHulianwangMianshiBaguwen/js/epub.min.map
InterviewtopHulianwangMianshiBaguwen/js/hooks.min.js
InterviewtopHulianwangMianshiBaguwen/js/hooks.min.map
InterviewtopHulianwangMianshiBaguwen/js/reader.js
InterviewtopHulianwangMianshiBaguwen/js/reader.js.map
interviewtop_hulianwang_mianshi_baguwen-2024.3.5.0.dist-info/METADATA
interviewtop_hulianwang_mianshi_baguwen-2024.3.5.0.dist-info/WHEEL
interviewtop_hulianwang_mianshi_baguwen-2024.3.5.0.dist-info/entry_points.txt
interviewtop_hulianwang_mianshi_baguwen-2024.3.5.0.dist-info/top_level.txt
interviewtop_hulianwang_mianshi_baguwen-2024.3.5.0.dist-info/RECORD
